{
  "currentResults": {
    "availableMandates": 0,
    "blankVotes": 1654,
    "blankVotesPercentage": 1.3,
    "displayMessage": null,
    "hasNoVoting": false,
    "nullVotes": 1170,
    "nullVotesPercentage": 0.92,
    "numberParishes": 208,
    "numberVoters": 127040,
    "percentageVoters": 53.82,
    "resultsParty": [
      {
        "absoluteMajority": null,
        "acronym": "PS",
        "constituenctyCounter": 1,
        "imageKey": "ps-logo",
        "mandates": 3,
        "percentage": 42.06,
        "presidents": null,
        "validVotesPercentage": 43.02,
        "votes": 53435
      },
      {
        "absoluteMajority": null,
        "acronym": "PPD/PSD",
        "constituenctyCounter": 1,
        "imageKey": "ppdpsd-logo",
        "mandates": 3,
        "percentage": 34.17,
        "presidents": null,
        "validVotesPercentage": 34.95,
        "votes": 43414
      },
      {
        "absoluteMajority": null,
        "acronym": "CH",
        "constituenctyCounter": 1,
        "imageKey": "ch-logo",
        "mandates": 0,
        "percentage": 6.06,
        "presidents": null,
        "validVotesPercentage": 6.2,
        "votes": 7702
      },
      {
        "absoluteMajority": null,
        "acronym": "B.E.",
        "constituenctyCounter": 1,
        "imageKey": "be-logo",
        "mandates": 0,
        "percentage": 3.48,
        "presidents": null,
        "validVotesPercentage": 3.56,
        "votes": 4418
      },
      {
        "absoluteMajority": null,
        "acronym": "CDS-PP",
        "constituenctyCounter": 1,
        "imageKey": "cdspp-logo",
        "mandates": 0,
        "percentage": 3.36,
        "presidents": null,
        "validVotesPercentage": 3.44,
        "votes": 4272
      },
      {
        "absoluteMajority": null,
        "acronym": "PCP-PEV",
        "constituenctyCounter": 1,
        "imageKey": "pcppev-logo",
        "mandates": 0,
        "percentage": 3.0,
        "presidents": null,
        "validVotesPercentage": 3.07,
        "votes": 3815
      },
      {
        "absoluteMajority": null,
        "acronym": "IL",
        "constituenctyCounter": 1,
        "imageKey": "il-logo",
        "mandates": 0,
        "percentage": 2.87,
        "presidents": null,
        "validVotesPercentage": 2.94,
        "votes": 3651
      },
      {
        "absoluteMajority": null,
        "acronym": "PAN",
        "constituenctyCounter": 1,
        "imageKey": "pan-logo",
        "mandates": 0,
        "percentage": 0.98,
        "presidents": null,
        "validVotesPercentage": 1.01,
        "votes": 1251
      },
      {
        "absoluteMajority": null,
        "acronym": "L",
        "constituenctyCounter": 1,
        "imageKey": "l-logo",
        "mandates": 0,
        "percentage": 0.72,
        "presidents": null,
        "validVotesPercentage": 0.74,
        "votes": 919
      },
      {
        "absoluteMajority": null,
        "acronym": "R.I.R.",
        "constituenctyCounter": 1,
        "imageKey": "rir-logo",
        "mandates": 0,
        "percentage": 0.44,
        "presidents": null,
        "validVotesPercentage": 0.45,
        "votes": 556
      },
      {
        "absoluteMajority": null,
        "acronym": "MPT",
        "constituenctyCounter": 1,
        "imageKey": "mpt-logo",
        "mandates": 0,
        "percentage": 0.15,
        "presidents": null,
        "validVotesPercentage": 0.15,
        "votes": 190
      },
      {
        "absoluteMajority": null,
        "acronym": "A",
        "constituenctyCounter": 1,
        "imageKey": "a-logo",
        "mandates": 0,
        "percentage": 0.14,
        "presidents": null,
        "validVotesPercentage": 0.14,
        "votes": 173
      },
      {
        "absoluteMajority": null,
        "acronym": "MAS",
        "constituenctyCounter": 1,
        "imageKey": "mas-logo",
        "mandates": 0,
        "percentage": 0.12,
        "presidents": null,
        "validVotesPercentage": 0.13,
        "votes": 157
      },
      {
        "absoluteMajority": null,
        "acronym": "E",
        "constituenctyCounter": 1,
        "imageKey": "e-logo",
        "mandates": 0,
        "percentage": 0.1,
        "presidents": null,
        "validVotesPercentage": 0.11,
        "votes": 133
      },
      {
        "absoluteMajority": null,
        "acronym": "VP",
        "constituenctyCounter": 1,
        "imageKey": "vp-logo",
        "mandates": 0,
        "percentage": 0.1,
        "presidents": null,
        "validVotesPercentage": 0.1,
        "votes": 130
      }
    ],
    "subscribedVoters": 236042,
    "tie": false,
    "tieMessage": null,
    "totalBoycotts": 0,
    "totalForeignBoycotts": 0,
    "totalLocalBoycotts": 0,
    "totalMandates": 6,
    "totalParishesApproved": 208,
    "totalVoters": 127040
  },
  "displayMessage": null,
  "foreignCounterMessage": null,
  "nationalCounterMessage": null,
  "previousResults": {
    "blankVotes": 3617,
    "blankVotesPercentage": 2.97,
    "displayMessage": null,
    "nullVotes": 2199,
    "nullVotesPercentage": 1.8,
    "percentageVoters": 50.6,
    "resultsParty": [
      {
        "absoluteMajority": null,
        "acronym": "PS",
        "constituenctyCounter": null,
        "imageKey": "ps-logo_old",
        "mandates": 3,
        "percentage": 34.77,
        "presidents": null,
        "validVotesPercentage": 36.51,
        "votes": 42392
      },
      {
        "absoluteMajority": null,
        "acronym": "PPD/PSD",
        "constituenctyCounter": null,
        "imageKey": "ppdpsd-logo_old",
        "mandates": 3,
        "percentage": 33.79,
        "presidents": null,
        "validVotesPercentage": 35.48,
        "votes": 41196
      },
      {
        "absoluteMajority": null,
        "acronym": "B.E.",
        "constituenctyCounter": null,
        "imageKey": "be-logo_old",
        "mandates": 0,
        "percentage": 8.47,
        "presidents": null,
        "validVotesPercentage": 8.89,
        "votes": 10320
      },
      {
        "absoluteMajority": null,
        "acronym": "CDS-PP",
        "constituenctyCounter": null,
        "imageKey": "cdspp-logo_old",
        "mandates": 0,
        "percentage": 6.21,
        "presidents": null,
        "validVotesPercentage": 6.53,
        "votes": 7576
      },
      {
        "absoluteMajority": null,
        "acronym": "PCP-PEV",
        "constituenctyCounter": null,
        "imageKey": "pcppev-logo_old",
        "mandates": 0,
        "percentage": 3.97,
        "presidents": null,
        "validVotesPercentage": 4.17,
        "votes": 4839
      },
      {
        "absoluteMajority": null,
        "acronym": "PAN",
        "constituenctyCounter": null,
        "imageKey": "pan-logo_old",
        "mandates": 0,
        "percentage": 2.36,
        "presidents": null,
        "validVotesPercentage": 2.48,
        "votes": 2876
      },
      {
        "absoluteMajority": null,
        "acronym": "R.I.R.",
        "constituenctyCounter": null,
        "imageKey": "rir-logo_old",
        "mandates": 0,
        "percentage": 0.87,
        "presidents": null,
        "validVotesPercentage": 0.91,
        "votes": 1058
      },
      {
        "absoluteMajority": null,
        "acronym": "CH",
        "constituenctyCounter": null,
        "imageKey": "ch-logo_old",
        "mandates": 0,
        "percentage": 0.7,
        "presidents": null,
        "validVotesPercentage": 0.74,
        "votes": 858
      },
      {
        "absoluteMajority": null,
        "acronym": "IL",
        "constituenctyCounter": null,
        "imageKey": "il-logo_old",
        "mandates": 0,
        "percentage": 0.57,
        "presidents": null,
        "validVotesPercentage": 0.6,
        "votes": 692
      },
      {
        "absoluteMajority": null,
        "acronym": "A",
        "constituenctyCounter": null,
        "imageKey": "a-logo_old",
        "mandates": 0,
        "percentage": 0.56,
        "presidents": null,
        "validVotesPercentage": 0.58,
        "votes": 679
      },
      {
        "absoluteMajority": null,
        "acronym": "L",
        "constituenctyCounter": null,
        "imageKey": "l-logo_old",
        "mandates": 0,
        "percentage": 0.56,
        "presidents": null,
        "validVotesPercentage": 0.59,
        "votes": 688
      },
      {
        "absoluteMajority": null,
        "acronym": "PCTP/MRPP",
        "constituenctyCounter": null,
        "imageKey": "pctpmrpp-logo_old",
        "mandates": 0,
        "percentage": 0.55,
        "presidents": null,
        "validVotesPercentage": 0.58,
        "votes": 671
      },
      {
        "absoluteMajority": null,
        "acronym": "JPP",
        "constituenctyCounter": null,
        "imageKey": "jpp-logo_old",
        "mandates": 0,
        "percentage": 0.48,
        "presidents": null,
        "validVotesPercentage": 0.51,
        "votes": 587
      },
      {
        "absoluteMajority": null,
        "acronym": "PNR",
        "constituenctyCounter": null,
        "imageKey": "pnr-logo_old",
        "mandates": 0,
        "percentage": 0.24,
        "presidents": null,
        "validVotesPercentage": 0.25,
        "votes": 292
      },
      {
        "absoluteMajority": null,
        "acronym": "PDR",
        "constituenctyCounter": null,
        "imageKey": "pdr-logo_old",
        "mandates": 0,
        "percentage": 0.23,
        "presidents": null,
        "validVotesPercentage": 0.24,
        "votes": 281
      },
      {
        "absoluteMajority": null,
        "acronym": "NC",
        "constituenctyCounter": null,
        "imageKey": "nc-logo_old",
        "mandates": 0,
        "percentage": 0.21,
        "presidents": null,
        "validVotesPercentage": 0.22,
        "votes": 259
      },
      {
        "absoluteMajority": null,
        "acronym": "MPT",
        "constituenctyCounter": null,
        "imageKey": "mpt-logo_old",
        "mandates": 0,
        "percentage": 0.17,
        "presidents": null,
        "validVotesPercentage": 0.18,
        "votes": 209
      },
      {
        "absoluteMajority": null,
        "acronym": "PPM",
        "constituenctyCounter": null,
        "imageKey": "ppm-logo_old",
        "mandates": 0,
        "percentage": 0.17,
        "presidents": null,
        "validVotesPercentage": 0.18,
        "votes": 204
      },
      {
        "absoluteMajority": null,
        "acronym": "PTP",
        "constituenctyCounter": null,
        "imageKey": "ptp-logo_old",
        "mandates": 0,
        "percentage": 0.17,
        "presidents": null,
        "validVotesPercentage": 0.18,
        "votes": 208
      },
      {
        "absoluteMajority": null,
        "acronym": "PURP",
        "constituenctyCounter": null,
        "imageKey": "purp-logo_old",
        "mandates": 0,
        "percentage": 0.17,
        "presidents": null,
        "validVotesPercentage": 0.18,
        "votes": 212
      }
    ],
    "subscribedVoters": 240917,
    "totalMandates": 6,
    "totalVoters": 121913
  },
  "refreshTimeout": 20,
  "territoryFullName": "Viana do Castelo",
  "territoryKey": "LOCAL-160000",
  "territoryMessage": null,
  "territoryName": "Viana do Castelo",
  "time": "17:03",
  "timeOnServer": 0,
  "totalConsulates": 31,
  "totalConsulatesApproved": 31,
  "totalParishes": 3092,
  "totalParishesApproved": 3092,
  "warningMessage": null
}
